odoo/addons/member_card/README.rst
odoo/addons/member_card/__init__.py
odoo/addons/member_card/__manifest__.py
odoo/addons/member_card/i18n/fr.po
odoo/addons/member_card/i18n/member_card.pot
odoo/addons/member_card/models/__init__.py
odoo/addons/member_card/models/membercard.py
odoo/addons/member_card/models/partner.py
odoo/addons/member_card/models/res_company.py
odoo/addons/member_card/readme/CONTRIBUTORS.rst
odoo/addons/member_card/readme/DESCRIPTION.rst
odoo/addons/member_card/readme/ROADMAP.rst
odoo/addons/member_card/report/member_card_template.xml
odoo/addons/member_card/security/ir.model.access.csv
odoo/addons/member_card/static/description/index.html
odoo/addons/member_card/tests/__init__.py
odoo/addons/member_card/tests/test_member_card.py
odoo/addons/member_card/views/partner.xml
odoo/addons/member_card/views/res_company_view.xml
odoo/addons/member_card/wizard/__init__.py
odoo/addons/member_card/wizard/member_card_wizards.py
odoo/addons/member_card/wizard/member_card_wizards_views.xml
odoo_addon_member_card-16.0.1.0.0.7.dist-info/METADATA
odoo_addon_member_card-16.0.1.0.0.7.dist-info/WHEEL
odoo_addon_member_card-16.0.1.0.0.7.dist-info/top_level.txt
odoo_addon_member_card-16.0.1.0.0.7.dist-info/RECORD
