Metadata-Version: 2.1
Name: odoo-addon-member_card
Version: 16.0.1.0.0.7
Requires-Python: >=3.10
Requires-Dist: odoo>=16.0a,<16.1dev
Summary: Create a member card and link it to a partner.
Home-page: https://github.com/beescoop/Obeesdoo
License: AGPL-3
Author: BEES coop - Cellule IT, Coop IT Easy SC
Classifier: Programming Language :: Python
Classifier: Framework :: Odoo
Classifier: Framework :: Odoo :: 16.0
Classifier: License :: OSI Approved :: GNU Affero General Public License v3
